flake8_numpy_random.py
flake8_numpy_random-0.1.0.dist-info/entry_points.txt
flake8_numpy_random-0.1.0.dist-info/LICENSE
flake8_numpy_random-0.1.0.dist-info/WHEEL
flake8_numpy_random-0.1.0.dist-info/METADATA
flake8_numpy_random-0.1.0.dist-info/RECORD
